{"_type":"export","__export_format":4,"__export_date":"2022-08-17T00:55:48.306Z","__export_source":"insomnia.desktop.app:v2022.5.0","resources":[{"_id":"req_65236d4c16924ad8ba1772e9a1f00922","parentId":"fld_5a81cefba2b646648ac15955b1555229","modified":1660586103303,"created":1660585961219,"url":"{{ _.local_url }}/customers/getAll","name":"GetAll","description":"","method":"GET","body":{},"parameters":[],"headers":[],"authentication":{},"metaSortKey":-1660585961219,"isPrivate":false,"settingStoreCookies":true,"settingSendCookies":true,"settingDisableRenderRequestBody":false,"settingEncodeUrl":true,"settingRebuildPath":true,"settingFollowRedirects":"global","_type":"request"},{"_id":"fld_5a81cefba2b646648ac15955b1555229","parentId":"wrk_6c7ded6e67cf4363912bc6faeaa7f866","modified":1660585958819,"created":1660585958819,"name":"Customers","description":"","environment":{},"environmentPropertyOrder":null,"metaSortKey":-1660585958819,"_type":"request_group"},{"_id":"wrk_6c7ded6e67cf4363912bc6faeaa7f866","parentId":null,"modified":1660586252553,"created":1660585646272,"name":"New Document","description":"If black than code API s´ring project","scope":"design","_type":"workspace"},{"_id":"req_c12b7ec122fc4d1e92659e0c3ef5fdc5","parentId":"fld_5a81cefba2b646648ac15955b1555229","modified":1660586154131,"created":1660586133215,"url":"{{ _.local_url }}/customers/createCustomer","name":"Create Customer","description":"","method":"POST","body":{"mimeType":"application/json","text":"{\n    \"name\": \"Cliente03\",\n    \"email\": \"email@email.com\",\n    \"cpf\": \"9999999999292\"\n}"},"parameters":[],"headers":[{"name":"Content-Type","value":"application/json","id":"pair_4b5bec6bfa5447f883aebc5d89f8041a"}],"authentication":{},"metaSortKey":-1660585961169,"isPrivate":false,"settingStoreCookies":true,"settingSendCookies":true,"settingDisableRenderRequestBody":false,"settingEncodeUrl":true,"settingRebuildPath":true,"settingFollowRedirects":"global","_type":"request"},{"_id":"req_9209fa1aa16a45b5b757c28f8f7ba5cb","parentId":"fld_5a81cefba2b646648ac15955b1555229","modified":1660589350257,"created":1660589318316,"url":"{{ _.local_url }}/customers/updateCustomer","name":"Update Customer","description":"","method":"PUT","body":{"mimeType":"application/json","text":"{\n    \"id\": 1,\n    \"name\": \"OtherClient01\",\n    \"email\": \"mail@gmail.com\",\n    \"cpf\": \"999999999999\"\n}"},"parameters":[],"headers":[{"name":"Content-Type","value":"application/json","id":"pair_4b5bec6bfa5447f883aebc5d89f8041a"}],"authentication":{},"metaSortKey":-1660585961119,"isPrivate":false,"settingStoreCookies":true,"settingSendCookies":true,"settingDisableRenderRequestBody":false,"settingEncodeUrl":true,"settingRebuildPath":true,"settingFollowRedirects":"global","_type":"request"},{"_id":"req_92558dc0e8a94833b7f6eec9ca0c6ea4","parentId":"fld_5a81cefba2b646648ac15955b1555229","modified":1660589582588,"created":1660589397125,"url":"{{ _.local_url }}/customers/findById","name":"Find by Id","description":"","method":"POST","body":{"mimeType":"application/json","text":"{\n    \"id\": 1\n}"},"parameters":[],"headers":[{"name":"Content-Type","value":"application/json","id":"pair_4b5bec6bfa5447f883aebc5d89f8041a"}],"authentication":{},"metaSortKey":-1660585961144,"isPrivate":false,"settingStoreCookies":true,"settingSendCookies":true,"settingDisableRenderRequestBody":false,"settingEncodeUrl":true,"settingRebuildPath":true,"settingFollowRedirects":"global","_type":"request"},{"_id":"req_7472c192018241c7b3642c24bd421f41","parentId":"fld_5a81cefba2b646648ac15955b1555229","modified":1660589561540,"created":1660589555049,"url":"{{ _.local_url }}/customers/getTransactions","name":"Get Transactions","description":"","method":"POST","body":{"mimeType":"application/json","text":"{\n    \"id\": 1\n}"},"parameters":[],"headers":[{"name":"Content-Type","value":"application/json","id":"pair_4b5bec6bfa5447f883aebc5d89f8041a"}],"authentication":{},"metaSortKey":-1660585961131.5,"isPrivate":false,"settingStoreCookies":true,"settingSendCookies":true,"settingDisableRenderRequestBody":false,"settingEncodeUrl":true,"settingRebuildPath":true,"settingFollowRedirects":"global","_type":"request"},{"_id":"req_c87fb4ca8b4a40b2ae8be9195caf68c2","parentId":"fld_5a81cefba2b646648ac15955b1555229","modified":1660589580764,"created":1660589575692,"url":"{{ _.local_url }}/customers/deleteById","name":"Delete by Id","description":"","method":"DELETE","body":{"mimeType":"application/json","text":"{\n    \"id\": 1\n}"},"parameters":[],"headers":[{"name":"Content-Type","value":"application/json","id":"pair_4b5bec6bfa5447f883aebc5d89f8041a"}],"authentication":{},"metaSortKey":-1660585961137.75,"isPrivate":false,"settingStoreCookies":true,"settingSendCookies":true,"settingDisableRenderRequestBody":false,"settingEncodeUrl":true,"settingRebuildPath":true,"settingFollowRedirects":"global","_type":"request"},{"_id":"req_6092b497fecd41d59612926ca273c304","parentId":"fld_70d3b18c20054fa8850406e008a669b5","modified":1660589615588,"created":1660589601073,"url":"{{ _.local_url }}/products/getAll","name":"GetAll","description":"","method":"GET","body":{},"parameters":[],"headers":[],"authentication":{},"metaSortKey":-1660585961219,"isPrivate":false,"settingStoreCookies":true,"settingSendCookies":true,"settingDisableRenderRequestBody":false,"settingEncodeUrl":true,"settingRebuildPath":true,"settingFollowRedirects":"global","_type":"request"},{"_id":"fld_70d3b18c20054fa8850406e008a669b5","parentId":"wrk_6c7ded6e67cf4363912bc6faeaa7f866","modified":1660589601070,"created":1660589601070,"name":"Product","description":"","environment":{},"environmentPropertyOrder":null,"metaSortKey":-1660585958769,"_type":"request_group"},{"_id":"req_4fcae5c29c7f46a79b21dd5fb3824b92","parentId":"fld_70d3b18c20054fa8850406e008a669b5","modified":1660589837996,"created":1660589601076,"url":"{{ _.local_url }}/products/createProduct","name":"Create Product","description":"","method":"POST","body":{"mimeType":"application/json","text":"{\n    \"name\": \"Prednisona\",\n    \"price\": 7.5,\n    \"isGeneric\": false,\n    \"amountInStock\": 100\n}"},"parameters":[],"headers":[{"name":"Content-Type","value":"application/json","id":"pair_4b5bec6bfa5447f883aebc5d89f8041a"}],"authentication":{},"metaSortKey":-1660585961169,"isPrivate":false,"settingStoreCookies":true,"settingSendCookies":true,"settingDisableRenderRequestBody":false,"settingEncodeUrl":true,"settingRebuildPath":true,"settingFollowRedirects":"global","_type":"request"},{"_id":"req_926097b717694f0ca9eb3dad607c699c","parentId":"fld_70d3b18c20054fa8850406e008a669b5","modified":1660589834504,"created":1660589601079,"url":"{{ _.local_url }}/products/updateProduct","name":"Update Product","description":"","method":"PUT","body":{"mimeType":"application/json","text":"{\n    \"id\": 1,\n    \"name\": \"Prednisona\",\n    \"isGeneric\": true,\n    \"amountInStock\": 5\n}"},"parameters":[],"headers":[{"name":"Content-Type","value":"application/json","id":"pair_4b5bec6bfa5447f883aebc5d89f8041a"}],"authentication":{},"metaSortKey":-1660585961119,"isPrivate":false,"settingStoreCookies":true,"settingSendCookies":true,"settingDisableRenderRequestBody":false,"settingEncodeUrl":true,"settingRebuildPath":true,"settingFollowRedirects":"global","_type":"request"},{"_id":"req_045652a5b38c4737925f2a7d3dd9f41a","parentId":"fld_70d3b18c20054fa8850406e008a669b5","modified":1660589837281,"created":1660589601082,"url":"{{ _.local_url }}/products/findById","name":"Find by Id","description":"","method":"POST","body":{"mimeType":"application/json","text":"{\n    \"id\": 1\n}"},"parameters":[],"headers":[{"name":"Content-Type","value":"application/json","id":"pair_4b5bec6bfa5447f883aebc5d89f8041a"}],"authentication":{},"metaSortKey":-1660585961144,"isPrivate":false,"settingStoreCookies":true,"settingSendCookies":true,"settingDisableRenderRequestBody":false,"settingEncodeUrl":true,"settingRebuildPath":true,"settingFollowRedirects":"global","_type":"request"},{"_id":"req_1981e50c53c74c209c0aac7d5eead240","parentId":"fld_70d3b18c20054fa8850406e008a669b5","modified":1660589835912,"created":1660589601086,"url":"{{ _.local_url }}/products/deleteById","name":"Delete by Id","description":"","method":"DELETE","body":{"mimeType":"application/json","text":"{\n    \"id\": 1\n}"},"parameters":[],"headers":[{"name":"Content-Type","value":"application/json","id":"pair_4b5bec6bfa5447f883aebc5d89f8041a"}],"authentication":{},"metaSortKey":-1660585961137.75,"isPrivate":false,"settingStoreCookies":true,"settingSendCookies":true,"settingDisableRenderRequestBody":false,"settingEncodeUrl":true,"settingRebuildPath":true,"settingFollowRedirects":"global","_type":"request"},{"_id":"req_0de7aea14a7e46fc86ecedcd5a5985e3","parentId":"fld_f5d77296d14b40ea9c6c806115597783","modified":1660589857951,"created":1660589789124,"url":"{{ _.local_url }}/orders/getAll","name":"GetAll","description":"","method":"GET","body":{},"parameters":[],"headers":[],"authentication":{},"metaSortKey":-1660585961219,"isPrivate":false,"settingStoreCookies":true,"settingSendCookies":true,"settingDisableRenderRequestBody":false,"settingEncodeUrl":true,"settingRebuildPath":true,"settingFollowRedirects":"global","_type":"request"},{"_id":"fld_f5d77296d14b40ea9c6c806115597783","parentId":"wrk_6c7ded6e67cf4363912bc6faeaa7f866","modified":1660589789121,"created":1660589789121,"name":"Order","description":"","environment":{},"environmentPropertyOrder":null,"metaSortKey":-1660585958719,"_type":"request_group"},{"_id":"req_fd21d4853b534437a035933f5be4e227","parentId":"fld_f5d77296d14b40ea9c6c806115597783","modified":1660589888555,"created":1660589789128,"url":"{{ _.local_url }}/orders/createOrder","name":"Create Product","description":"","method":"POST","body":{"mimeType":"application/json","text":"{\n    \"customerId\": 2,\n    \"sales\": [\n        {\n            \"productId\": 1,\n            \"amount\": 1\n        },\n        {\n            \"productId\": 2,\n            \"amount\": 2\n        },\n        {\n            \"productId\": 3,\n            \"amount\": 3\n        }\n    ]\n}\n"},"parameters":[],"headers":[{"name":"Content-Type","value":"application/json","id":"pair_4b5bec6bfa5447f883aebc5d89f8041a"}],"authentication":{},"metaSortKey":-1660585961169,"isPrivate":false,"settingStoreCookies":true,"settingSendCookies":true,"settingDisableRenderRequestBody":false,"settingEncodeUrl":true,"settingRebuildPath":true,"settingFollowRedirects":"global","_type":"request"},{"_id":"req_2ea2bb4dcec44ede82dabeefd96cde7e","parentId":"fld_f5d77296d14b40ea9c6c806115597783","modified":1660589888239,"created":1660589789134,"url":"{{ _.local_url }}/orders/findById","name":"Find by Id","description":"","method":"POST","body":{"mimeType":"application/json","text":"{\n    \"id\": 1\n}"},"parameters":[],"headers":[{"name":"Content-Type","value":"application/json","id":"pair_4b5bec6bfa5447f883aebc5d89f8041a"}],"authentication":{},"metaSortKey":-1660585961144,"isPrivate":false,"settingStoreCookies":true,"settingSendCookies":true,"settingDisableRenderRequestBody":false,"settingEncodeUrl":true,"settingRebuildPath":true,"settingFollowRedirects":"global","_type":"request"},{"_id":"req_38ddebce2c284987aa923aff1cef9ec6","parentId":"fld_f5d77296d14b40ea9c6c806115597783","modified":1660589887742,"created":1660589789136,"url":"{{ _.local_url }}/orders/deleteById","name":"Delete by Id","description":"","method":"DELETE","body":{"mimeType":"application/json","text":"{\n    \"id\": 1\n}"},"parameters":[],"headers":[{"name":"Content-Type","value":"application/json","id":"pair_4b5bec6bfa5447f883aebc5d89f8041a"}],"authentication":{},"metaSortKey":-1660585961137.75,"isPrivate":false,"settingStoreCookies":true,"settingSendCookies":true,"settingDisableRenderRequestBody":false,"settingEncodeUrl":true,"settingRebuildPath":true,"settingFollowRedirects":"global","_type":"request"},{"_id":"env_9d513c5f08b38c04124adc22b43261d52c58cb68","parentId":"wrk_6c7ded6e67cf4363912bc6faeaa7f866","modified":1660585866380,"created":1660585646292,"name":"Base Environment","data":{},"dataPropertyOrder":{},"color":null,"isPrivate":false,"metaSortKey":1660585646292,"_type":"environment"},{"_id":"jar_9d513c5f08b38c04124adc22b43261d52c58cb68","parentId":"wrk_6c7ded6e67cf4363912bc6faeaa7f866","modified":1660585646297,"created":1660585646297,"name":"Default Jar","cookies":[],"_type":"cookie_jar"},{"_id":"spc_66e88f79211e4ed190b0f38789f3e7c2","parentId":"wrk_6c7ded6e67cf4363912bc6faeaa7f866","modified":1660586239614,"created":1660585646287,"fileName":"ibtct3","contents":"","contentType":"yaml","_type":"api_spec"},{"_id":"uts_e8556cba19094725838abe1cd3ba99d9","parentId":"wrk_6c7ded6e67cf4363912bc6faeaa7f866","modified":1660585646303,"created":1660585646303,"name":"Example Test Suite","_type":"unit_test_suite"},{"_id":"env_7af2e370d52b4db781fa2e2d37bb2243","parentId":"env_9d513c5f08b38c04124adc22b43261d52c58cb68","modified":1660697711202,"created":1660585868414,"name":"Dev","data":{"local_url":"http://localhost:8080"},"dataPropertyOrder":{"&":["local_url"]},"color":null,"isPrivate":false,"metaSortKey":1660585868414,"_type":"environment"},{"_id":"env_cf020d1825924d9c8d6d39de4939a150","parentId":"env_9d513c5f08b38c04124adc22b43261d52c58cb68","modified":1660697713508,"created":1660585879238,"name":"Production","data":{"local_url":"https://ibtcg3-api.herokuapp.com"},"dataPropertyOrder":{"&":["local_url"]},"color":null,"isPrivate":false,"metaSortKey":1660585879238,"_type":"environment"}]}